setup.py
oneconsole/__init__.py
oneconsole.egg-info/PKG-INFO
oneconsole.egg-info/SOURCES.txt
oneconsole.egg-info/dependency_links.txt
oneconsole.egg-info/not-zip-safe
oneconsole.egg-info/pbr.json
oneconsole.egg-info/requires.txt
oneconsole.egg-info/top_level.txt