Metadata-Version: 1.0
Name: oneconsole
Version: 0.1.5
Summary: Python Package for Oneconsole
Home-page: http://github.com/sachinvettithanam/oneconsole
Author: Sachin Philip Mathew
Author-email: sachinvettithanam@gmail.com
License: MIT
Platform: UNKNOWN
